crianza/__init__.py
crianza/compiler.py
crianza/errors.py
crianza/genetic.py
crianza/instructions.py
crianza/interpreter.py
crianza/native.py
crianza/optimizer.py
crianza/parser.py
crianza/repl.py
crianza/stack.py
crianza/tokenizer.py
crianza-0.1.8.data/scripts/crianza
crianza-0.1.8.dist-info/DESCRIPTION.rst
crianza-0.1.8.dist-info/METADATA
crianza-0.1.8.dist-info/metadata.json
crianza-0.1.8.dist-info/RECORD
crianza-0.1.8.dist-info/top_level.txt
crianza-0.1.8.dist-info/WHEEL
crianza-0.1.8.dist-info/zip-safe
