Metadata-Version: 2.0
Name: crianza
Version: 0.1.8
Summary: Simple Forth-like VM and genetic programming framework.
Home-page: https://github.com/cslarsen/crianza
Author: Christian Stigen Larsen
Author-email: csl@csl.name
License: http://opensource.org/licenses/BSD-3-Clause
Download-URL: https://github.com/cslarsen/crianza/tarball/0.1.8
Keywords: vm,virtual machine,genetic programming,interpreter,forth,programming,code,bytecode,assembler,native,stack,machine,tanimoto,evolutionary programming,evolving,evolve,evolution,evolutionary,artificial intelligence,organism
Platform: unix
Platform: linux
Platform: osx
Platform: cygwin
Platform: win32
Classifier: Development Status :: 3 - Alpha
Classifier: Environment :: Console
Classifier: Intended Audience :: Developers
Classifier: Intended Audience :: Education
Classifier: License :: OSI Approved :: BSD License
Classifier: Natural Language :: English
Classifier: Operating System :: MacOS :: MacOS X
Classifier: Operating System :: Microsoft :: Windows
Classifier: Operating System :: POSIX
Classifier: Operating System :: Unix
Classifier: Programming Language :: Forth
Classifier: Programming Language :: Other
Classifier: Programming Language :: Python :: 2 :: Only
Classifier: Programming Language :: Python
Classifier: Topic :: Scientific/Engineering :: Artificial Intelligence
Classifier: Topic :: Software Development :: Code Generators
Classifier: Topic :: Software Development :: Compilers
Classifier: Topic :: Software Development :: Interpreters
Classifier: Topic :: Software Development :: Libraries
Classifier: Topic :: Utilities
